{
	"data": {
		"_id": "2016010101835848",
		"_status": "有效",
		"_title": "电线组件Cord set",
		"_type": "C_262",
		"产品名称": "电线组件Cord set",
		"制造商": "小米科技有限责任公司Xiaomi Inc.",
		"原因": "",
		"发证日期": "2016-01-11",
		"型号\/规格": "XMCT-01 10A 250V～ + XMLJQ-01 2.5A 250V～(配60227IEC53 3×0.75mm2)",
		"标准": "GB15934-2008",
		"现状态": "有效 Valid",
		"生产厂": "威海市泓淋电子有限公司Weihai Honglin Electronic Co., Ltd.",
		"申请人": "威海市泓淋电子有限公司Weihai Honglin Electronic Co., Ltd.",
		"证书截止日期": "2016-07-31",
		"证书状态变化时间": "",
		"证书编号": "2016010101835848",
		"附件": "",
		"首次发证日期": "2016-01-11"
	},
	"status": 200
}